vcspm/__init__.py
vcspm/decompress.py
vcspm/vcspm.py
vcspm/version.py
vcspm-1.0.4.dist-info/LICENSE
vcspm-1.0.4.dist-info/METADATA
vcspm-1.0.4.dist-info/WHEEL
vcspm-1.0.4.dist-info/entry_points.txt
vcspm-1.0.4.dist-info/top_level.txt
vcspm-1.0.4.dist-info/RECORD
