Metadata-Version: 2.1
Name: vcspm
Version: 1.0.4
Summary: Vinx的C/C++源码包管理器
Author-email: Vinx911 <Buddyhe911@163.com>
License: LGPL-2.1-or-later
Project-URL: Homepage, https://github.com/Vinx911/vcspm
Project-URL: Documentation, https://github.com/Vinx911/vcspm
Project-URL: Source, https://github.com/Vinx911/vcspm
Project-URL: Changelog, https://github.com/Vinx911/vcspm
Keywords: vcspm,C++,package manager
Classifier: Programming Language :: Python :: 3
Classifier: License :: OSI Approved :: GNU Lesser General Public License v2 or later (LGPLv2+)
Classifier: Operating System :: OS Independent
Requires-Python: >=3.7
License-File: LICENSE
Requires-Dist: paramiko ==3.3.1
Requires-Dist: py7zr ==0.20.6
Requires-Dist: pyzstd ==0.15.9
Requires-Dist: requests ==2.31.0
Requires-Dist: urllib3 ==2.0.4
Requires-Dist: scp ==0.14.5
